psf_parser/__init__.py
psf_parser/ascii/__init__.py
psf_parser/ascii/parser.py
psf_parser/ascii/token.py
psf_parser/binary/__init__.py
psf_parser/binary/chunk_id.py
psf_parser/binary/parser.py
psf_parser/binary/reader.py
psf_parser/declaration.py
psf_parser/file.py
psf_parser/parser.py
psf_parser/registry.py
psf_parser-0.2.1.dist-info/LICENSE
psf_parser-0.2.1.dist-info/METADATA
psf_parser-0.2.1.dist-info/WHEEL
psf_parser-0.2.1.dist-info/RECORD
