Metadata-Version: 2.3
Name: psf-parser
Version: 0.2.1
Summary: A pure-python parser for Cadence's PSF format.
License: MIT
Keywords: parser,parsing,cadence,spectre,psf,psfbin,psfascii
Author: ToonBettens
Author-email: toon.bettens@outlook.com
Requires-Python: >=3.10
Classifier: License :: OSI Approved :: MIT License
Classifier: Programming Language :: Python :: 3
Classifier: Programming Language :: Python :: 3.10
Classifier: Programming Language :: Python :: 3.11
Classifier: Programming Language :: Python :: 3.12
Classifier: Programming Language :: Python :: 3.13
Project-URL: Repository, https://github.com/ToonBettens/psf-parser
